devcron.py
devcron-0.4.data/scripts/devcron.py
devcron-0.4.dist-info/DESCRIPTION.rst
devcron-0.4.dist-info/METADATA
devcron-0.4.dist-info/RECORD
devcron-0.4.dist-info/WHEEL
devcron-0.4.dist-info/entry_points.txt
devcron-0.4.dist-info/metadata.json
devcron-0.4.dist-info/top_level.txt
